examples/10_exceptions.py
examples/11_jupyter_ndvi.py
examples/1_simple_add.py
examples/2_status.py
examples/3_stop.py
examples/4_priority.py
examples/5_retry.py
examples/6_batch.py
examples/7_mapreduce_sum.py
examples/8_ignore_map_error.py
examples/9_ndvi.py
examples/__init__.py
examples/lz.py
geocelery/__init__.py
geocelery/_/__init__.py
geocelery/_/application.py
geocelery/_/cookies.py
geocelery/_/settings.py
geocelery/_/tasks.py
geocelery/_/tokens.py
geocelery-1.1.dist-info/METADATA
geocelery-1.1.dist-info/WHEEL
geocelery-1.1.dist-info/top_level.txt
geocelery-1.1.dist-info/RECORD
