Metadata-Version: 2.1
Name: geocelery
Version: 1.1
Summary: UNKNOWN
Home-page: UNKNOWN
Author: zhouxiaohua
Author-email: zhouxiaohua@cnic.cn
License: UNKNOWN
Platform: UNKNOWN
Classifier: Programming Language :: Python :: 3
Classifier: License :: OSI Approved :: MIT License
Classifier: Operating System :: OS Independent
Requires-Dist: celery
Requires-Dist: redis (==2.10.6)
